{
  "IcoMoonType": "selection",
  "icons": [
    {
      "icon": {
        "paths": [
          "M384 554c0-70 58-128 128-128s128 58 128 128-58 128-128 128-128-58-128-128zM854 836l-164-164c22-34 36-74 36-118 0-118-96-212-214-212s-214 94-214 212 96 214 214 214c44 0 84-14 118-36l188 190c-14 10-30 16-50 16h-512c-46 0-86-38-86-84l2-684c0-46 38-84 84-84h342l256 256v494z"
        ],
        "attrs": [],
        "isMulticolor": false,
        "isMulticolor2": false,
        "tags": [
          "find_in_page"
        ],
        "defaultCode": 59520,
        "grid": 16
      },
      "attrs": [],
      "properties": {
        "order": 3,
        "ligatures": "find_in_page",
        "id": 857,
        "prevSize": 18,
        "code": 59541,
        "name": "find_in_page2"
      },
      "setIdx": 0,
      "setId": 0,
      "iconIdx": 0
    },
    {
      "icon": {
        "paths": [
          "M305.453 582.144c38.739 0 70.144-31.405 70.144-70.144s-31.405-70.144-70.144-70.144c-38.015 0.948-68.469 31.989-68.469 70.144s30.455 69.196 68.382 70.142zM502.838 447.987h424.512v128.196h-128.531v144.621h-138.659v-144.621h-157.322c-24.343 84.192-100.731 144.715-191.255 144.715-2.156 0-4.304-0.034-6.443-0.102-115.007 0.008-208.491-93.477-208.491-208.796s93.485-208.804 208.804-208.804c1.525-0.042 3.321-0.066 5.121-0.066 90.818 0 167.5 60.527 191.907 143.442z"
        ],
        "attrs": [
          {}
        ],
        "grid": 16,
        "tags": [
          "key"
        ],
        "isMulticolor": false,
        "isMulticolor2": false,
        "colorPermutations": {
          "13636361": [
            {}
          ]
        }
      },
      "attrs": [
        {}
      ],
      "properties": {
        "order": 4,
        "id": 855,
        "name": "key",
        "prevSize": 18,
        "code": 59654
      },
      "setIdx": 0,
      "setId": 0,
      "iconIdx": 1
    },
    {
      "icon": {
        "paths": [
          "M832 448h-256v-256h-128v256h-256v128h256v256h128v-256h256v-128z"
        ],
        "attrs": [
          {}
        ],
        "isMulticolor": false,
        "isMulticolor2": false,
        "grid": 16,
        "tags": [
          "add"
        ],
        "colorPermutations": {
          "13636361": [
            {}
          ]
        }
      },
      "attrs": [
        {}
      ],
      "properties": {
        "order": 5,
        "id": 854,
        "name": "add",
        "prevSize": 18,
        "code": 59658
      },
      "setIdx": 0,
      "setId": 0,
      "iconIdx": 2
    },
    {
      "icon": {
        "paths": [
          "M192 448h640v128h-640v-128z"
        ],
        "attrs": [
          {}
        ],
        "isMulticolor": false,
        "isMulticolor2": false,
        "grid": 16,
        "tags": [
          "remove"
        ],
        "colorPermutations": {
          "13636361": [
            {}
          ]
        }
      },
      "attrs": [
        {}
      ],
      "properties": {
        "order": 6,
        "id": 853,
        "name": "remove",
        "prevSize": 18,
        "code": 59659
      },
      "setIdx": 0,
      "setId": 0,
      "iconIdx": 3
    },
    {
      "icon": {
        "paths": [
          "M925.619 578.764v-137.185h-111.195c-8.492-36.612-22.241-68.912-40.626-97.988l79.405-77.707-97.383-97.564-77.912 78.554c-27.347-17.655-59.158-31.427-93.167-39.532l-2.085-112.535h-140.992v112.116c-36.023 8.489-67.774 22.228-96.274 40.58l-77-79.359-97.163 97.384 78.765 79.338c-17.592 27.792-31.308 60.1-39.345 94.591l-111.946 2.123v137.185h111.529c8.492 36.194 22.236 68.105 40.6 96.772l-79.378 77.161 97.383 97.274 77.741-78.666c27.299 17.611 59.058 31.337 93.012 39.393l2.074 111.031h140.993v-110.613c36.098-8.496 67.917-22.244 96.487-40.608l77.041 79.354 97.2-97.384-78.72-78.19c17.593-27.432 31.305-59.34 39.344-93.437zM512.327 750.056c-0 0-0 0-0.001 0-133.121 0-241.037-107.916-241.037-241.037s107.916-241.037 241.037-241.037c133.121 0 241.037 107.916 241.037 241.037-0.16 133.057-107.98 240.877-241.022 241.037z",
          "M615.633 509.002c0 57.052-46.25 103.302-103.302 103.302s-103.302-46.25-103.302-103.302c0-57.052 46.25-103.302 103.302-103.302s103.302 46.25 103.302 103.302z"
        ],
        "attrs": [
          {},
          {}
        ],
        "isMulticolor": false,
        "isMulticolor2": false,
        "grid": 16,
        "tags": [
          "settings"
        ],
        "colorPermutations": {
          "13636361": [
            {},
            {}
          ]
        }
      },
      "attrs": [
        {},
        {}
      ],
      "properties": {
        "order": 7,
        "id": 852,
        "name": "settings",
        "prevSize": 18,
        "code": 59660
      },
      "setIdx": 0,
      "setId": 0,
      "iconIdx": 4
    },
    {
      "icon": {
        "paths": [
          "M922.004 239.766c6.519-6.842 10.529-16.124 10.529-26.343s-4.011-19.501-10.544-26.358l-93.341-95.755c-6.527-6.668-15.62-10.802-25.679-10.802s-19.151 4.134-25.673 10.795l-69.993 71.772 144.623 148.364z",
          "M128 192v704h704v-384h-64v320h-576v-576h320v-64h-384z",
          "M495.936 677.312l314.112-322.688-144.64-148.352-314.112 322.688v148.352h144.64z"
        ],
        "attrs": [
          {},
          {},
          {}
        ],
        "grid": 16,
        "tags": [
          "edit"
        ],
        "isMulticolor": false,
        "isMulticolor2": false,
        "colorPermutations": {
          "13636361": [
            {},
            {},
            {}
          ]
        }
      },
      "attrs": [
        {},
        {},
        {}
      ],
      "properties": {
        "order": 8,
        "id": 851,
        "name": "edit",
        "prevSize": 18,
        "code": 59661
      },
      "setIdx": 0,
      "setId": 0,
      "iconIdx": 5
    },
    {
      "icon": {
        "paths": [
          "M418.419 884.149h-230.689v-372.149h-139.284l463.554-417.851 463.554 417.851h-139.284v372.149h-230.689v-278.567h-187.163v278.567z"
        ],
        "attrs": [],
        "isMulticolor": false,
        "isMulticolor2": false,
        "tags": [
          "home"
        ],
        "defaultCode": 59530,
        "grid": 16,
        "colorPermutations": {
          "13636361": []
        }
      },
      "attrs": [],
      "properties": {
        "order": 9,
        "ligatures": "home",
        "id": 845,
        "prevSize": 18,
        "code": 59530,
        "name": "home"
      },
      "setIdx": 0,
      "setId": 0,
      "iconIdx": 6
    },
    {
      "icon": {
        "paths": [
          "M406 598c106 0 192-86 192-192s-86-192-192-192-192 86-192 192 86 192 192 192zM662 598l212 212-64 64-212-212v-34l-12-12c-48 42-112 66-180 66-154 0-278-122-278-276s124-278 278-278 276 124 276 278c0 68-24 132-66 180l12 12h34z"
        ],
        "attrs": [],
        "isMulticolor": false,
        "isMulticolor2": false,
        "tags": [
          "search"
        ],
        "defaultCode": 59574,
        "grid": 16,
        "colorPermutations": {
          "13636361": []
        }
      },
      "attrs": [],
      "properties": {
        "order": 10,
        "ligatures": "search",
        "id": 655,
        "prevSize": 18,
        "code": 59574,
        "name": "search"
      },
      "setIdx": 0,
      "setId": 0,
      "iconIdx": 7
    },
    {
      "icon": {
        "paths": [
          "M512 426c46 0 86 40 86 86s-40 86-86 86-86-40-86-86 40-86 86-86zM768 426c46 0 86 40 86 86s-40 86-86 86-86-40-86-86 40-86 86-86zM256 426c46 0 86 40 86 86s-40 86-86 86-86-40-86-86 40-86 86-86z"
        ],
        "attrs": [],
        "isMulticolor": false,
        "isMulticolor2": false,
        "tags": [
          "more_horiz"
        ],
        "defaultCode": 58835,
        "grid": 16,
        "colorPermutations": {
          "13636361": []
        }
      },
      "attrs": [],
      "properties": {
        "order": 11,
        "ligatures": "more_horiz",
        "id": 846,
        "prevSize": 18,
        "code": 58835,
        "name": "more_horiz"
      },
      "setIdx": 0,
      "setId": 0,
      "iconIdx": 8
    },
    {
      "icon": {
        "paths": [
          "M512 682c46 0 86 40 86 86s-40 86-86 86-86-40-86-86 40-86 86-86zM512 426c46 0 86 40 86 86s-40 86-86 86-86-40-86-86 40-86 86-86zM512 342c-46 0-86-40-86-86s40-86 86-86 86 40 86 86-40 86-86 86z"
        ],
        "attrs": [],
        "isMulticolor": false,
        "isMulticolor2": false,
        "tags": [
          "more_vert"
        ],
        "defaultCode": 58836,
        "grid": 16,
        "colorPermutations": {
          "13636361": []
        }
      },
      "attrs": [],
      "properties": {
        "order": 12,
        "ligatures": "more_vert",
        "id": 847,
        "prevSize": 18,
        "code": 58836,
        "name": "more_vert"
      },
      "setIdx": 0,
      "setId": 0,
      "iconIdx": 9
    },
    {
      "icon": {
        "paths": [
          "M384 690l452-452 60 60-512 512-238-238 60-60z"
        ],
        "attrs": [],
        "isMulticolor": false,
        "isMulticolor2": false,
        "tags": [
          "check"
        ],
        "defaultCode": 58826,
        "grid": 16,
        "colorPermutations": {
          "13636361": []
        }
      },
      "attrs": [],
      "properties": {
        "order": 13,
        "ligatures": "check",
        "id": 148,
        "prevSize": 18,
        "code": 58826,
        "name": "check"
      },
      "setIdx": 0,
      "setId": 0,
      "iconIdx": 10
    },
    {
      "icon": {
        "paths": [
          "M945.047 255.759c-1.16-0.737-2.516-1.467-3.925-2.101l-0.208-0.084-415.997-183.884c-3.808-1.718-8.256-2.719-12.938-2.719s-9.129 1.001-13.141 2.8l-415.267 183.57c-1.8 0.765-3.324 1.575-4.771 2.496-8.898 5.671-14.8 15.628-14.8 26.963 0 0.008 0 0.016 0 0.024l-0 450.077c0.019 12.663 7.378 23.602 18.050 28.793l416.538 198.325c3.742 1.792 8.126 2.87 12.754 2.944l0.108 0 0.526 0.004 0.526-0.004h0.083c4.653-0.074 9.038-1.152 12.969-3.025l0.599-0.294 415.58-197.866c10.87-5.271 18.237-16.209 18.267-28.872l0-450.082c-0.001-11.347-5.913-21.313-14.823-26.987zM511.977 133.942l339.328 149.968-339.328 161.619-339.331-161.619zM127.992 333.512l351.955 167.631v379.136l-351.955-167.566zM896.008 712.712l-352.072 167.569v-379.136l352.070-167.631z"
        ],
        "attrs": [],
        "grid": 16,
        "tags": [
          "module"
        ],
        "isMulticolor": false,
        "isMulticolor2": false,
        "colorPermutations": {
          "13636361": []
        }
      },
      "attrs": [],
      "properties": {
        "order": 14,
        "id": 849,
        "name": "module",
        "prevSize": 18,
        "code": 59655
      },
      "setIdx": 0,
      "setId": 0,
      "iconIdx": 11
    },
    {
      "icon": {
        "paths": [
          "M884 300l-78 78-160-160 78-78c16-16 44-16 60 0l100 100c16 16 16 44 0 60zM128 736l472-472 160 160-472 472h-160v-160z"
        ],
        "attrs": [],
        "isMulticolor": false,
        "isMulticolor2": false,
        "tags": [
          "mode_edit"
        ],
        "defaultCode": 57940,
        "grid": 16,
        "colorPermutations": {
          "13636361": []
        }
      },
      "attrs": [],
      "properties": {
        "order": 15,
        "ligatures": "create, edit, mode_edit",
        "id": 184,
        "prevSize": 18,
        "code": 57940,
        "name": "mode_edit"
      },
      "setIdx": 0,
      "setId": 0,
      "iconIdx": 12
    },
    {
      "icon": {
        "paths": [
          "M810 274l-238 238 238 238-60 60-238-238-238 238-60-60 238-238-238-238 60-60 238 238 238-238z"
        ],
        "attrs": [],
        "isMulticolor": false,
        "isMulticolor2": false,
        "tags": [
          "close"
        ],
        "defaultCode": 58829,
        "grid": 16,
        "colorPermutations": {
          "13636361": []
        }
      },
      "attrs": [],
      "properties": {
        "order": 16,
        "ligatures": "clear, close",
        "id": 157,
        "prevSize": 18,
        "code": 58829,
        "name": "close"
      },
      "setIdx": 0,
      "setId": 0,
      "iconIdx": 13
    },
    {
      "icon": {
        "paths": [
          "M298 426h428l-214 214z"
        ],
        "attrs": [],
        "isMulticolor": false,
        "isMulticolor2": false,
        "tags": [
          "arrow_drop_down"
        ],
        "defaultCode": 58821,
        "grid": 16,
        "colorPermutations": {
          "13636361": []
        }
      },
      "attrs": [],
      "properties": {
        "order": 17,
        "ligatures": "arrow_drop_down",
        "id": 47,
        "prevSize": 18,
        "code": 58821,
        "name": "arrow_drop_down"
      },
      "setIdx": 0,
      "setId": 0,
      "iconIdx": 14
    },
    {
      "icon": {
        "paths": [
          "M298 598l214-214 214 214h-428z"
        ],
        "attrs": [],
        "isMulticolor": false,
        "isMulticolor2": false,
        "tags": [
          "arrow_drop_up"
        ],
        "defaultCode": 58823,
        "grid": 16,
        "colorPermutations": {
          "13636361": []
        }
      },
      "attrs": [],
      "properties": {
        "order": 18,
        "ligatures": "arrow_drop_up",
        "id": 49,
        "prevSize": 18,
        "code": 58823,
        "name": "arrow_drop_up"
      },
      "setIdx": 0,
      "setId": 0,
      "iconIdx": 15
    },
    {
      "icon": {
        "paths": [
          "M896 640v256h-256l98-98-124-122 62-62 122 124zM384 896h-256v-256l98 98 122-124 62 62-124 122zM128 384v-256h256l-98 98 124 122-62 62-122-124zM640 128h256v256l-98-98-122 124-62-62 124-122z"
        ],
        "attrs": [],
        "isMulticolor": false,
        "isMulticolor2": false,
        "tags": [
          "zoom_out_map"
        ],
        "defaultCode": 58731,
        "grid": 16,
        "colorPermutations": {
          "13636361": []
        }
      },
      "attrs": [],
      "properties": {
        "order": 67,
        "ligatures": "zoom_out_map",
        "id": 844,
        "prevSize": 18,
        "code": 58731,
        "name": "zoom_out_map"
      },
      "setIdx": 0,
      "setId": 0,
      "iconIdx": 16
    },
    {
      "icon": {
        "paths": [
          "M854 470v84h-520l238 240-60 60-342-342 342-342 60 60-238 240h520z"
        ],
        "attrs": [],
        "isMulticolor": false,
        "isMulticolor2": false,
        "tags": [
          "arrow_back"
        ],
        "defaultCode": 58820,
        "grid": 16,
        "colorPermutations": {
          "13636361": []
        }
      },
      "attrs": [],
      "properties": {
        "order": 68,
        "ligatures": "arrow_back",
        "id": 45,
        "prevSize": 18,
        "code": 58820,
        "name": "arrow_back"
      },
      "setIdx": 0,
      "setId": 0,
      "iconIdx": 17
    },
    {
      "icon": {
        "paths": [
          "M512 170l342 342-342 342-60-60 238-240h-520v-84h520l-238-240z"
        ],
        "attrs": [],
        "isMulticolor": false,
        "isMulticolor2": false,
        "tags": [
          "arrow_forward"
        ],
        "defaultCode": 58824,
        "grid": 16,
        "colorPermutations": {
          "13636361": []
        }
      },
      "attrs": [],
      "properties": {
        "order": 69,
        "ligatures": "arrow_forward",
        "id": 50,
        "prevSize": 18,
        "code": 58824,
        "name": "arrow_forward"
      },
      "setIdx": 0,
      "setId": 0,
      "iconIdx": 18
    },
    {
      "icon": {
        "paths": [
          "M170 512l342-342 342 342-62 60-238-238v520h-84v-520l-240 238z"
        ],
        "attrs": [],
        "isMulticolor": false,
        "isMulticolor2": false,
        "tags": [
          "arrow_upward"
        ],
        "defaultCode": 58840,
        "grid": 16,
        "colorPermutations": {
          "13636361": []
        }
      },
      "attrs": [],
      "properties": {
        "order": 70,
        "ligatures": "arrow_upward",
        "id": 51,
        "prevSize": 18,
        "code": 58840,
        "name": "arrow_upward"
      },
      "setIdx": 0,
      "setId": 0,
      "iconIdx": 19
    },
    {
      "icon": {
        "paths": [
          "M854 512l-342 342-342-342 62-60 238 238v-520h84v520l240-238z"
        ],
        "attrs": [],
        "isMulticolor": false,
        "isMulticolor2": false,
        "tags": [
          "arrow_downward"
        ],
        "defaultCode": 58843,
        "grid": 16,
        "colorPermutations": {
          "13636361": []
        }
      },
      "attrs": [],
      "properties": {
        "order": 71,
        "ligatures": "arrow_downward",
        "id": 46,
        "prevSize": 18,
        "code": 58843,
        "name": "arrow_downward"
      },
      "setIdx": 0,
      "setId": 0,
      "iconIdx": 20
    },
    {
      "icon": {
        "paths": [
          "M682 554c100 0 300 50 300 150v106h-256v-106c0-64-34-112-84-148 14-2 28-2 40-2zM342 554c100 0 298 50 298 150v106h-598v-106c0-100 200-150 300-150zM342 470c-70 0-128-58-128-128s58-128 128-128 126 58 126 128-56 128-126 128zM682 470c-70 0-128-58-128-128s58-128 128-128 128 58 128 128-58 128-128 128z"
        ],
        "attrs": [],
        "isMulticolor": false,
        "isMulticolor2": false,
        "tags": [
          "people"
        ],
        "defaultCode": 59387,
        "grid": 16,
        "colorPermutations": {
          "13636361": []
        }
      },
      "attrs": [],
      "properties": {
        "order": 19,
        "ligatures": "group, people",
        "id": 368,
        "prevSize": 18,
        "code": 59387,
        "name": "people"
      },
      "setIdx": 0,
      "setId": 0,
      "iconIdx": 21
    },
    {
      "icon": {
        "paths": [
          "M554 554c86 0 256 42 256 128v86h-512v-86c0-86 170-128 256-128zM838 562c86 14 186 54 186 120v86h-128v-86c0-50-22-88-58-120zM554 470c-70 0-128-58-128-128s58-128 128-128 128 58 128 128-58 128-128 128zM768 470c-14 0-26-2-38-6 24-34 38-76 38-122s-14-88-38-122c12-4 24-6 38-6 70 0 128 58 128 128s-58 128-128 128zM342 426v86h-128v128h-86v-128h-128v-86h128v-128h86v128h128z"
        ],
        "attrs": [],
        "isMulticolor": false,
        "isMulticolor2": false,
        "tags": [
          "group_add"
        ],
        "defaultCode": 59376,
        "grid": 16,
        "colorPermutations": {
          "13636361": []
        }
      },
      "attrs": [],
      "properties": {
        "order": 20,
        "ligatures": "group_add",
        "id": 369,
        "prevSize": 18,
        "code": 59376,
        "name": "group_add"
      },
      "setIdx": 0,
      "setId": 0,
      "iconIdx": 22
    },
    {
      "icon": {
        "paths": [
          "M682 342h128v84h-212v-212h84v128zM598 810v-212h212v84h-128v128h-84zM342 342v-128h84v212h-212v-84h128zM214 682v-84h212v212h-84v-128h-128z"
        ],
        "attrs": [],
        "isMulticolor": false,
        "isMulticolor2": false,
        "tags": [
          "fullscreen_exit"
        ],
        "defaultCode": 58833,
        "grid": 16,
        "colorPermutations": {
          "13636361": []
        }
      },
      "attrs": [],
      "properties": {
        "order": 21,
        "ligatures": "fullscreen_exit",
        "id": 350,
        "prevSize": 18,
        "code": 58833,
        "name": "fullscreen_exit"
      },
      "setIdx": 0,
      "setId": 0,
      "iconIdx": 23
    },
    {
      "icon": {
        "paths": [
          "M598 214h212v212h-84v-128h-128v-84zM726 726v-128h84v212h-212v-84h128zM214 426v-212h212v84h-128v128h-84zM298 598v128h128v84h-212v-212h84z"
        ],
        "attrs": [],
        "isMulticolor": false,
        "isMulticolor2": false,
        "tags": [
          "fullscreen"
        ],
        "defaultCode": 58832,
        "grid": 16,
        "colorPermutations": {
          "13636361": []
        }
      },
      "attrs": [],
      "properties": {
        "order": 22,
        "ligatures": "fullscreen",
        "id": 349,
        "prevSize": 18,
        "code": 58832,
        "name": "fullscreen"
      },
      "setIdx": 0,
      "setId": 0,
      "iconIdx": 24
    },
    {
      "icon": {
        "paths": [
          "M214 768h596v86h-596v-86zM384 682v-256h-170l298-298 298 298h-170v256h-256z"
        ],
        "attrs": [],
        "isMulticolor": false,
        "isMulticolor2": false,
        "tags": [
          "file_upload"
        ],
        "defaultCode": 58054,
        "grid": 16,
        "colorPermutations": {
          "13636361": []
        }
      },
      "attrs": [],
      "properties": {
        "order": 23,
        "ligatures": "file_upload",
        "id": 280,
        "prevSize": 18,
        "code": 58054,
        "name": "file_upload"
      },
      "setIdx": 0,
      "setId": 0,
      "iconIdx": 25
    },
    {
      "icon": {
        "paths": [
          "M214 768h596v86h-596v-86zM810 384l-298 298-298-298h170v-256h256v256h170z"
        ],
        "attrs": [],
        "isMulticolor": false,
        "isMulticolor2": false,
        "tags": [
          "file_download"
        ],
        "defaultCode": 59524,
        "grid": 16,
        "colorPermutations": {
          "13636361": []
        }
      },
      "attrs": [],
      "properties": {
        "order": 24,
        "ligatures": "file_download, get_app",
        "id": 279,
        "prevSize": 18,
        "code": 59524,
        "name": "file_download"
      },
      "setIdx": 0,
      "setId": 0,
      "iconIdx": 26
    },
    {
      "icon": {
        "paths": [
          "M512 342h64v180l150 90-32 52-182-110v-212zM554 128c212 0 384 172 384 384s-172 384-384 384c-106 0-200-42-270-112l60-62c54 54 128 88 210 88 166 0 300-132 300-298s-134-298-300-298-298 132-298 298h128l-172 172-4-6-166-166h128c0-212 172-384 384-384z"
        ],
        "attrs": [],
        "isMulticolor": false,
        "isMulticolor2": false,
        "tags": [
          "restore"
        ],
        "defaultCode": 59571,
        "grid": 16,
        "colorPermutations": {
          "13636361": []
        }
      },
      "attrs": [],
      "properties": {
        "order": 25,
        "ligatures": "history, restore",
        "id": 385,
        "prevSize": 18,
        "code": 59571,
        "name": "restore"
      },
      "setIdx": 0,
      "setId": 0,
      "iconIdx": 27
    },
    {
      "icon": {
        "paths": [
          "M534 298v224l192 114-32 54-224-136v-256h64zM512 854c188 0 342-154 342-342s-154-342-342-342-342 154-342 342 154 342 342 342zM512 86c236 0 426 190 426 426s-190 426-426 426-426-190-426-426 190-426 426-426z"
        ],
        "attrs": [],
        "isMulticolor": false,
        "isMulticolor2": false,
        "tags": [
          "schedule"
        ],
        "defaultCode": 59573,
        "grid": 16,
        "colorPermutations": {
          "13636361": []
        }
      },
      "attrs": [],
      "properties": {
        "order": 26,
        "ligatures": "access_time, query_builder, schedule",
        "id": 4,
        "prevSize": 18,
        "code": 59573,
        "name": "schedule"
      },
      "setIdx": 0,
      "setId": 0,
      "iconIdx": 28
    },
    {
      "icon": {
        "paths": [
          "M512 776l136-136 60 60-196 196-196-196 60-60zM512 248l-136 136-60-60 196-196 196 196-60 60z"
        ],
        "attrs": [],
        "isMulticolor": false,
        "isMulticolor2": false,
        "tags": [
          "unfold_more"
        ],
        "defaultCode": 58839,
        "grid": 16,
        "colorPermutations": {
          "13636361": []
        }
      },
      "attrs": [],
      "properties": {
        "order": 27,
        "ligatures": "unfold_more",
        "id": 786,
        "prevSize": 18,
        "code": 58839,
        "name": "unfold_more"
      },
      "setIdx": 0,
      "setId": 0,
      "iconIdx": 29
    },
    {
      "icon": {
        "paths": [
          "M708 230l-196 196-196-196 60-60 136 136 136-136zM316 794l196-196 196 196-60 60-136-136-136 136z"
        ],
        "attrs": [],
        "isMulticolor": false,
        "isMulticolor2": false,
        "tags": [
          "unfold_less"
        ],
        "defaultCode": 58838,
        "grid": 16,
        "colorPermutations": {
          "13636361": []
        }
      },
      "attrs": [],
      "properties": {
        "order": 28,
        "ligatures": "unfold_less",
        "id": 785,
        "prevSize": 18,
        "code": 58838,
        "name": "unfold_less"
      },
      "setIdx": 0,
      "setId": 0,
      "iconIdx": 30
    },
    {
      "icon": {
        "paths": [
          "M658 316l-196 196 196 196-60 60-256-256 256-256z"
        ],
        "attrs": [],
        "isMulticolor": false,
        "isMulticolor2": false,
        "tags": [
          "navigate_before"
        ],
        "defaultCode": 58376,
        "grid": 16,
        "colorPermutations": {
          "13636361": []
        }
      },
      "attrs": [],
      "properties": {
        "order": 29,
        "ligatures": "chevron_left, navigate_before",
        "id": 152,
        "prevSize": 18,
        "code": 58376,
        "name": "navigate_before"
      },
      "setIdx": 0,
      "setId": 0,
      "iconIdx": 31
    },
    {
      "icon": {
        "paths": [
          "M426 256l256 256-256 256-60-60 196-196-196-196z"
        ],
        "attrs": [],
        "isMulticolor": false,
        "isMulticolor2": false,
        "tags": [
          "navigate_next"
        ],
        "defaultCode": 58377,
        "grid": 16,
        "colorPermutations": {
          "13636361": []
        }
      },
      "attrs": [],
      "properties": {
        "order": 30,
        "ligatures": "chevron_right, navigate_next",
        "id": 153,
        "prevSize": 18,
        "code": 58377,
        "name": "navigate_next"
      },
      "setIdx": 0,
      "setId": 0,
      "iconIdx": 32
    },
    {
      "icon": {
        "paths": [
          "M512 342l256 256-60 60-196-196-196 196-60-60z"
        ],
        "attrs": [],
        "isMulticolor": false,
        "isMulticolor2": false,
        "tags": [
          "expand_less"
        ],
        "defaultCode": 58830,
        "grid": 16,
        "colorPermutations": {
          "13636361": []
        }
      },
      "attrs": [],
      "properties": {
        "order": 31,
        "ligatures": "expand_less",
        "id": 255,
        "prevSize": 18,
        "code": 58830,
        "name": "expand_less"
      },
      "setIdx": 0,
      "setId": 0,
      "iconIdx": 33
    },
    {
      "icon": {
        "paths": [
          "M708 366l60 60-256 256-256-256 60-60 196 196z"
        ],
        "attrs": [],
        "isMulticolor": false,
        "isMulticolor2": false,
        "tags": [
          "expand_more"
        ],
        "defaultCode": 58831,
        "grid": 16,
        "colorPermutations": {
          "13636361": []
        }
      },
      "attrs": [],
      "properties": {
        "order": 32,
        "ligatures": "expand_more",
        "id": 256,
        "prevSize": 18,
        "code": 58831,
        "name": "expand_more"
      },
      "setIdx": 0,
      "setId": 0,
      "iconIdx": 34
    },
    {
      "icon": {
        "paths": [
          "M298 598c46 0 86-40 86-86s-40-86-86-86-84 40-84 86 38 86 84 86zM540 426h442v172h-86v170h-170v-170h-186c-34 100-130 170-242 170-142 0-256-114-256-256s114-256 256-256c112 0 208 70 242 170z"
        ],
        "attrs": [],
        "isMulticolor": false,
        "isMulticolor2": false,
        "tags": [
          "vpn_key"
        ],
        "defaultCode": 57562,
        "grid": 16,
        "colorPermutations": {
          "13636361": []
        }
      },
      "attrs": [],
      "properties": {
        "order": 33,
        "ligatures": "vpn_key",
        "id": 821,
        "prevSize": 18,
        "code": 57562,
        "name": "vpn_key"
      },
      "setIdx": 0,
      "setId": 0,
      "iconIdx": 35
    },
    {
      "icon": {
        "paths": [
          "M512 820c106 0 200-56 256-138-2-84-172-132-256-132-86 0-254 48-256 132 56 82 150 138 256 138zM512 214c-70 0-128 58-128 128s58 128 128 128 128-58 128-128-58-128-128-128zM512 86c236 0 426 190 426 426s-190 426-426 426-426-190-426-426 190-426 426-426z"
        ],
        "attrs": [],
        "isMulticolor": false,
        "isMulticolor2": false,
        "tags": [
          "account_circle"
        ],
        "defaultCode": 59475,
        "grid": 16,
        "colorPermutations": {
          "13636361": []
        }
      },
      "attrs": [],
      "properties": {
        "order": 34,
        "ligatures": "account_circle",
        "id": 10,
        "prevSize": 18,
        "code": 59475,
        "name": "account_circle"
      },
      "setIdx": 0,
      "setId": 0,
      "iconIdx": 36
    },
    {
      "icon": {
        "paths": [
          "M256 726v42h512v-42c0-86-170-132-256-132s-256 46-256 132zM640 384c0-70-58-128-128-128s-128 58-128 128 58 128 128 128 128-58 128-128zM128 214c0-46 38-86 86-86h596c46 0 86 40 86 86v596c0 46-40 86-86 86h-596c-48 0-86-40-86-86v-596z"
        ],
        "attrs": [],
        "isMulticolor": false,
        "isMulticolor2": false,
        "tags": [
          "account_box"
        ],
        "defaultCode": 59473,
        "grid": 16,
        "colorPermutations": {
          "13636361": []
        }
      },
      "attrs": [],
      "properties": {
        "order": 72,
        "ligatures": "account_box",
        "id": 9,
        "prevSize": 18,
        "code": 59473,
        "name": "account_box"
      },
      "setIdx": 0,
      "setId": 0,
      "iconIdx": 37
    },
    {
      "icon": {
        "paths": [
          "M810 554h-256v256h-84v-256h-256v-84h256v-256h84v256h256v84z"
        ],
        "attrs": [],
        "isMulticolor": false,
        "isMulticolor2": false,
        "tags": [
          "plus"
        ],
        "defaultCode": 57669,
        "grid": 16,
        "colorPermutations": {
          "13636361": []
        }
      },
      "attrs": [],
      "properties": {
        "order": 73,
        "ligatures": "add",
        "id": 12,
        "prevSize": 18,
        "code": 57669,
        "name": "plus"
      },
      "setIdx": 0,
      "setId": 0,
      "iconIdx": 38
    },
    {
      "icon": {
        "paths": [
          "M810 554h-596v-84h596v84z"
        ],
        "attrs": [],
        "isMulticolor": false,
        "isMulticolor2": false,
        "tags": [
          "minus"
        ],
        "defaultCode": 57691,
        "grid": 16,
        "colorPermutations": {
          "13636361": []
        }
      },
      "attrs": [],
      "properties": {
        "order": 74,
        "ligatures": "remove",
        "id": 617,
        "prevSize": 18,
        "code": 57691,
        "name": "minus"
      },
      "setIdx": 0,
      "setId": 0,
      "iconIdx": 39
    },
    {
      "icon": {
        "paths": [
          "M726 554v-84h-172v-172h-84v172h-172v84h172v172h84v-172h172zM810 128c46 0 86 40 86 86v596c0 46-40 86-86 86h-596c-48 0-86-40-86-86v-596c0-46 38-86 86-86h596z"
        ],
        "attrs": [],
        "isMulticolor": false,
        "isMulticolor2": false,
        "tags": [
          "add_box"
        ],
        "defaultCode": 57670,
        "grid": 16,
        "colorPermutations": {
          "13636361": []
        }
      },
      "attrs": [],
      "properties": {
        "order": 75,
        "ligatures": "add_box",
        "id": 16,
        "prevSize": 18,
        "code": 57670,
        "name": "add_box"
      },
      "setIdx": 0,
      "setId": 0,
      "iconIdx": 40
    },
    {
      "icon": {
        "paths": [
          "M726 554v-84h-172v-172h-84v172h-172v84h172v172h84v-172h172zM512 86c236 0 426 190 426 426s-190 426-426 426-426-190-426-426 190-426 426-426z"
        ],
        "attrs": [],
        "isMulticolor": false,
        "isMulticolor2": false,
        "tags": [
          "add_circle"
        ],
        "defaultCode": 57671,
        "grid": 16,
        "colorPermutations": {
          "13636361": []
        }
      },
      "attrs": [],
      "properties": {
        "order": 76,
        "ligatures": "add_circle",
        "id": 17,
        "prevSize": 18,
        "code": 57671,
        "name": "add_circle"
      },
      "setIdx": 0,
      "setId": 0,
      "iconIdx": 41
    },
    {
      "icon": {
        "paths": [
          "M512 854c188 0 342-154 342-342s-154-342-342-342-342 154-342 342 154 342 342 342zM512 86c236 0 426 190 426 426s-190 426-426 426-426-190-426-426 190-426 426-426zM554 298v172h172v84h-172v172h-84v-172h-172v-84h172v-172h84z"
        ],
        "attrs": [],
        "isMulticolor": false,
        "isMulticolor2": false,
        "tags": [
          "control_point"
        ],
        "defaultCode": 58298,
        "grid": 16,
        "colorPermutations": {
          "13636361": []
        }
      },
      "attrs": [],
      "properties": {
        "order": 35,
        "ligatures": "add_circle_outline, control_point",
        "id": 18,
        "prevSize": 18,
        "code": 58298,
        "name": "control_point"
      },
      "setIdx": 0,
      "setId": 0,
      "iconIdx": 42
    },
    {
      "icon": {
        "paths": [
          "M726 768c46 0 84 40 84 86s-38 84-84 84-86-38-86-84 40-86 86-86zM42 86h140l40 84h632c24 0 42 20 42 44 0 8-2 14-6 20l-152 276c-14 26-42 44-74 44h-318l-38 70-2 6c0 6 4 10 10 10h494v86h-512c-46 0-84-40-84-86 0-14 4-28 10-40l58-106-154-324h-86v-84zM298 768c46 0 86 40 86 86s-40 84-86 84-84-38-84-84 38-86 84-86z"
        ],
        "attrs": [],
        "isMulticolor": false,
        "isMulticolor2": false,
        "tags": [
          "shopping_cart"
        ],
        "defaultCode": 59596,
        "grid": 16,
        "colorPermutations": {
          "13636361": []
        }
      },
      "attrs": [],
      "properties": {
        "order": 36,
        "ligatures": "local_grocery_store, shopping_cart",
        "id": 456,
        "prevSize": 18,
        "code": 59596,
        "name": "shopping_cart"
      },
      "setIdx": 0,
      "setId": 0,
      "iconIdx": 43
    },
    {
      "icon": {
        "paths": [
          "M306 630c0 6 4 10 10 10h494v86h-512c-46 0-84-40-84-86 0-14 4-28 10-40l58-106-154-324h-86v-84h140c27.003 56.33 53.665 113.001 80 170 34.063 71.271 67.603 143.063 102 214h300c54.786-99.881 110.533-198.8 164-300l74 42-164 298c-14 26-42 44-74 44h-318l-38 70zM726 768c46 0 84 40 84 86s-38 84-84 84-86-38-86-84 40-86 86-86zM298 768c46 0 86 40 86 86s-40 84-86 84-84-38-84-84 38-86 84-86zM470 384v-128h-128v-86h128v-128h84v128h128v86h-128v128h-84z"
        ],
        "attrs": [],
        "isMulticolor": false,
        "isMulticolor2": false,
        "tags": [
          "add_shopping_cart"
        ],
        "defaultCode": 59476,
        "grid": 16,
        "colorPermutations": {
          "13636361": []
        }
      },
      "attrs": [],
      "properties": {
        "order": 37,
        "ligatures": "add_shopping_cart",
        "id": 20,
        "prevSize": 18,
        "code": 59476,
        "name": "add_shopping_cart"
      },
      "setIdx": 0,
      "setId": 0,
      "iconIdx": 44
    },
    {
      "icon": {
        "paths": [
          "M810 470v-86h-170v-170h-86v170h-170v86h170v170h86v-170h170zM854 86c46 0 84 38 84 84v512c0 46-38 86-84 86h-512c-46 0-86-40-86-86v-512c0-46 40-84 86-84h512zM170 256v598h598v84h-598c-46 0-84-38-84-84v-598h84z"
        ],
        "attrs": [],
        "isMulticolor": false,
        "isMulticolor2": false,
        "tags": [
          "queue"
        ],
        "defaultCode": 57404,
        "grid": 16,
        "colorPermutations": {
          "13636361": []
        }
      },
      "attrs": [],
      "properties": {
        "order": 38,
        "ligatures": "add_to_photos, library_add, queue",
        "id": 21,
        "prevSize": 18,
        "code": 57404,
        "name": "queue"
      },
      "setIdx": 0,
      "setId": 0,
      "iconIdx": 45
    },
    {
      "icon": {
        "paths": [
          "M554 640v-86h-84v86h84zM554 470v-256h-84v256h84zM854 86c46 0 84 38 84 84v512c0 46-38 86-84 86h-598l-170 170v-768c0-46 38-84 84-84h684z"
        ],
        "attrs": [],
        "isMulticolor": false,
        "isMulticolor2": false,
        "tags": [
          "announcement"
        ],
        "defaultCode": 59482,
        "grid": 16,
        "colorPermutations": {
          "13636361": []
        }
      },
      "attrs": [],
      "properties": {
        "order": 39,
        "ligatures": "announcement",
        "id": 42,
        "prevSize": 18,
        "code": 59482,
        "name": "announcement"
      },
      "setIdx": 0,
      "setId": 0,
      "iconIdx": 46
    },
    {
      "icon": {
        "paths": [
          "M682 854v-172h172v172h-172zM682 598v-172h172v172h-172zM426 342v-172h172v172h-172zM682 170h172v172h-172v-172zM426 598v-172h172v172h-172zM170 598v-172h172v172h-172zM170 854v-172h172v172h-172zM426 854v-172h172v172h-172zM170 342v-172h172v172h-172z"
        ],
        "attrs": [],
        "isMulticolor": false,
        "isMulticolor2": false,
        "tags": [
          "apps"
        ],
        "defaultCode": 58819,
        "grid": 16,
        "colorPermutations": {
          "13636361": []
        }
      },
      "attrs": [],
      "properties": {
        "order": 40,
        "ligatures": "apps",
        "id": 43,
        "prevSize": 18,
        "code": 58819,
        "name": "apps"
      },
      "setIdx": 0,
      "setId": 0,
      "iconIdx": 47
    },
    {
      "icon": {
        "paths": [
          "M218 214h588l-40-44h-512zM512 746l234-234h-148v-86h-172v86h-148zM876 224c12 14 20 34 20 54v532c0 46-40 86-86 86h-596c-46 0-86-40-86-86v-532c0-20 8-40 20-54l58-72c12-14 30-24 50-24h512c20 0 38 10 50 24z"
        ],
        "attrs": [],
        "isMulticolor": false,
        "isMulticolor2": false,
        "tags": [
          "archive"
        ],
        "defaultCode": 57673,
        "grid": 16,
        "colorPermutations": {
          "13636361": []
        }
      },
      "attrs": [],
      "properties": {
        "order": 41,
        "ligatures": "archive",
        "id": 44,
        "prevSize": 18,
        "code": 57673,
        "name": "archive"
      },
      "setIdx": 0,
      "setId": 0,
      "iconIdx": 48
    },
    {
      "icon": {
        "paths": [
          "M0 854h1024v170h-1024v-170zM810 490c0 0 86 94 86 150 0 46-40 86-86 86s-84-40-84-86c0-56 84-150 84-150zM222 426h410l-206-204zM706 382c26 26 26 66 0 90l-234 234c-12 12-30 20-46 20s-32-8-44-20l-236-234c-26-24-26-64 0-90l220-220-102-102 62-60z"
        ],
        "attrs": [],
        "isMulticolor": false,
        "isMulticolor2": false,
        "tags": [
          "format_color_fill"
        ],
        "defaultCode": 57914,
        "grid": 16,
        "colorPermutations": {
          "13636361": []
        }
      },
      "attrs": [],
      "properties": {
        "order": 42,
        "ligatures": "format_color_fill",
        "id": 326,
        "prevSize": 18,
        "code": 57914,
        "name": "format_color_fill"
      },
      "setIdx": 0,
      "setId": 0,
      "iconIdx": 49
    },
    {
      "icon": {
        "paths": [
          "M128 256h768v86h-768v-86zM128 554v-84h768v84h-768zM128 768v-86h768v86h-768z"
        ],
        "attrs": [],
        "isMulticolor": false,
        "isMulticolor2": false,
        "tags": [
          "menu"
        ],
        "defaultCode": 58834,
        "grid": 16,
        "colorPermutations": {
          "13636361": []
        }
      },
      "attrs": [],
      "properties": {
        "order": 43,
        "ligatures": "menu",
        "id": 489,
        "prevSize": 18,
        "code": 58834,
        "name": "menu"
      },
      "setIdx": 0,
      "setId": 0,
      "iconIdx": 50
    },
    {
      "icon": {
        "paths": [
          "M298 214h598v84h-598v-84zM298 554v-84h598v84h-598zM298 810v-84h598v84h-598zM170 704c36 0 64 30 64 64s-30 64-64 64-64-30-64-64 28-64 64-64zM170 192c36 0 64 28 64 64s-28 64-64 64-64-28-64-64 28-64 64-64zM170 448c36 0 64 28 64 64s-28 64-64 64-64-28-64-64 28-64 64-64z"
        ],
        "attrs": [],
        "isMulticolor": false,
        "isMulticolor2": false,
        "tags": [
          "format_list_bulleted"
        ],
        "defaultCode": 57921,
        "grid": 16,
        "colorPermutations": {
          "13636361": []
        }
      },
      "attrs": [],
      "properties": {
        "order": 44,
        "ligatures": "format_list_bulleted",
        "id": 333,
        "prevSize": 18,
        "code": 57923,
        "name": "format_list_bulleted2"
      },
      "setIdx": 0,
      "setId": 0,
      "iconIdx": 51
    },
    {
      "icon": {
        "paths": [
          "M426 554v-84h512v84h-512zM426 810v-84h512v84h-512zM426 214h512v84h-512v-84zM256 298v428h106l-148 148-150-148h106v-428h-106l150-148 148 148h-106z"
        ],
        "attrs": [],
        "isMulticolor": false,
        "isMulticolor2": false,
        "tags": [
          "format_line_spacing"
        ],
        "defaultCode": 57920,
        "grid": 16,
        "colorPermutations": {
          "13636361": []
        }
      },
      "attrs": [],
      "properties": {
        "order": 45,
        "ligatures": "format_line_spacing",
        "id": 332,
        "prevSize": 18,
        "code": 57920,
        "name": "format_line_spacing"
      },
      "setIdx": 0,
      "setId": 0,
      "iconIdx": 52
    },
    {
      "icon": {
        "paths": [
          "M598 726l84-172h-128v-256h256v256l-84 172h-128zM256 726l86-172h-128v-256h256v256l-86 172h-128z"
        ],
        "attrs": [],
        "isMulticolor": false,
        "isMulticolor2": false,
        "tags": [
          "format_quote"
        ],
        "defaultCode": 57924,
        "grid": 16,
        "colorPermutations": {
          "13636361": []
        }
      },
      "attrs": [],
      "properties": {
        "order": 46,
        "ligatures": "format_quote",
        "id": 336,
        "prevSize": 18,
        "code": 57924,
        "name": "format_quote"
      },
      "setIdx": 0,
      "setId": 0,
      "iconIdx": 53
    },
    {
      "icon": {
        "paths": [
          "M410 512h204l-102-270zM470 128h84l234 598h-96l-46-128h-268l-48 128h-96zM0 854h1024v170h-1024v-170z"
        ],
        "attrs": [],
        "isMulticolor": false,
        "isMulticolor2": false,
        "tags": [
          "format_color_text"
        ],
        "defaultCode": 57916,
        "grid": 16,
        "colorPermutations": {
          "13636361": []
        }
      },
      "attrs": [],
      "properties": {
        "order": 47,
        "ligatures": "format_color_text",
        "id": 328,
        "prevSize": 18,
        "code": 57916,
        "name": "format_color_text"
      },
      "setIdx": 0,
      "setId": 0,
      "iconIdx": 54
    },
    {
      "icon": {
        "paths": [
          "M622 708l198-196-198-196 60-60 256 256-256 256zM402 708l-60 60-256-256 256-256 60 60-198 196z"
        ],
        "attrs": [],
        "isMulticolor": false,
        "isMulticolor2": false,
        "tags": [
          "code"
        ],
        "defaultCode": 59503,
        "grid": 16,
        "colorPermutations": {
          "13636361": []
        }
      },
      "attrs": [],
      "properties": {
        "order": 48,
        "ligatures": "code",
        "id": 166,
        "prevSize": 18,
        "code": 59503,
        "name": "code"
      },
      "setIdx": 0,
      "setId": 0,
      "iconIdx": 55
    },
    {
      "icon": {
        "paths": [
          "M800 330c34 52 54 116 54 182 0 188-154 342-342 342v128l-170-172 170-170v128c142 0 256-114 256-256 0-44-12-84-30-120zM512 256c-142 0-256 114-256 256 0 44 10 84 30 120l-62 62c-34-52-54-116-54-182 0-188 154-342 342-342v-128l170 172-170 170v-128z"
        ],
        "attrs": [],
        "isMulticolor": false,
        "isMulticolor2": false,
        "tags": [
          "autorenew"
        ],
        "defaultCode": 59491,
        "grid": 16,
        "colorPermutations": {
          "13636361": []
        }
      },
      "attrs": [],
      "properties": {
        "order": 49,
        "ligatures": "autorenew",
        "id": 67,
        "prevSize": 18,
        "code": 59491,
        "name": "autorenew"
      },
      "setIdx": 0,
      "setId": 0,
      "iconIdx": 56
    },
    {
      "icon": {
        "paths": [
          "M512 854c188 0 342-154 342-342s-154-342-342-342-342 154-342 342 154 342 342 342zM512 86c236 0 426 190 426 426s-190 426-426 426-426-190-426-426 190-426 426-426zM298 470h428v84h-428v-84z"
        ],
        "attrs": [],
        "isMulticolor": false,
        "isMulticolor2": false,
        "tags": [
          "remove_circle_outline"
        ],
        "defaultCode": 57693,
        "grid": 16,
        "colorPermutations": {
          "13636361": []
        }
      },
      "attrs": [],
      "properties": {
        "order": 50,
        "ligatures": "remove_circle_outline",
        "id": 618,
        "prevSize": 18,
        "code": 57693,
        "name": "remove_circle_outline"
      },
      "setIdx": 0,
      "setId": 0,
      "iconIdx": 57
    },
    {
      "icon": {
        "paths": [
          "M726 554v-84h-428v84h428zM512 86c236 0 426 190 426 426s-190 426-426 426-426-190-426-426 190-426 426-426z"
        ],
        "attrs": [],
        "isMulticolor": false,
        "isMulticolor2": false,
        "tags": [
          "remove_circle"
        ],
        "defaultCode": 57692,
        "grid": 16,
        "colorPermutations": {
          "13636361": []
        }
      },
      "attrs": [],
      "properties": {
        "order": 77,
        "ligatures": "do_not_disturb_on, remove_circle",
        "id": 230,
        "prevSize": 18,
        "code": 57692,
        "name": "remove_circle"
      },
      "setIdx": 0,
      "setId": 0,
      "iconIdx": 58
    },
    {
      "icon": {
        "paths": [
          "M512 854c188 0 342-154 342-342s-154-342-342-342-342 154-342 342 154 342 342 342zM512 86c236 0 426 190 426 426s-190 426-426 426-426-190-426-426 190-426 426-426zM622 342l60 60-110 110 110 110-60 60-110-110-110 110-60-60 110-110-110-110 60-60 110 110z"
        ],
        "attrs": [],
        "isMulticolor": false,
        "isMulticolor2": false,
        "tags": [
          "highlight_off"
        ],
        "defaultCode": 59528,
        "grid": 16,
        "colorPermutations": {
          "13636361": []
        }
      },
      "attrs": [],
      "properties": {
        "order": 78,
        "ligatures": "highlight_off",
        "id": 384,
        "prevSize": 18,
        "code": 59528,
        "name": "highlight_off"
      },
      "setIdx": 0,
      "setId": 0,
      "iconIdx": 59
    },
    {
      "icon": {
        "paths": [
          "M512 256c94 0 170 76 170 170 0 106-128 118-128 214h-84c0-138 128-128 128-214 0-46-40-84-86-84s-86 38-86 84h-84c0-94 76-170 170-170zM512 854c188 0 342-154 342-342s-154-342-342-342-342 154-342 342 154 342 342 342zM512 86c236 0 426 190 426 426s-190 426-426 426-426-190-426-426 190-426 426-426zM470 768v-86h84v86h-84z"
        ],
        "attrs": [],
        "isMulticolor": false,
        "isMulticolor2": false,
        "tags": [
          "help_outline"
        ],
        "defaultCode": 59645,
        "grid": 16,
        "colorPermutations": {
          "13636361": []
        }
      },
      "attrs": [],
      "properties": {
        "order": 79,
        "ligatures": "help_outline",
        "id": 381,
        "prevSize": 18,
        "code": 59645,
        "name": "help_outline"
      },
      "setIdx": 0,
      "setId": 0,
      "iconIdx": 60
    },
    {
      "icon": {
        "paths": [
          "M642 480c24-24 40-58 40-96 0-94-76-170-170-170s-170 76-170 170h84c0-46 40-86 86-86s86 40 86 86c0 24-10 44-26 60l-52 54c-30 32-50 74-50 120v22h84c0-64 20-88 50-120zM554 810v-84h-84v84h84zM512 86c236 0 426 190 426 426s-190 426-426 426-426-190-426-426 190-426 426-426z"
        ],
        "attrs": [],
        "isMulticolor": false,
        "isMulticolor2": false,
        "tags": [
          "help"
        ],
        "defaultCode": 59527,
        "grid": 16,
        "colorPermutations": {
          "13636361": []
        }
      },
      "attrs": [],
      "properties": {
        "order": 80,
        "ligatures": "help",
        "id": 380,
        "prevSize": 18,
        "code": 59527,
        "name": "help"
      },
      "setIdx": 0,
      "setId": 0,
      "iconIdx": 61
    },
    {
      "icon": {
        "paths": [
          "M512 854c188 0 342-154 342-342s-154-342-342-342-342 154-342 342 154 342 342 342zM512 86c236 0 426 190 426 426s-190 426-426 426-426-190-426-426 190-426 426-426zM470 298h84v256h-84v-256zM470 640h84v86h-84v-86z"
        ],
        "attrs": [],
        "isMulticolor": false,
        "isMulticolor2": false,
        "tags": [
          "error_outline"
        ],
        "defaultCode": 57345,
        "grid": 16,
        "colorPermutations": {
          "13636361": []
        }
      },
      "attrs": [],
      "properties": {
        "order": 81,
        "ligatures": "error_outline",
        "id": 246,
        "prevSize": 18,
        "code": 57345,
        "name": "error_outline"
      },
      "setIdx": 0,
      "setId": 0,
      "iconIdx": 62
    },
    {
      "icon": {
        "paths": [
          "M554 554v-256h-84v256h84zM554 726v-86h-84v86h84zM512 86c236 0 426 190 426 426s-190 426-426 426-426-190-426-426 190-426 426-426z"
        ],
        "attrs": [],
        "isMulticolor": false,
        "isMulticolor2": false,
        "tags": [
          "error"
        ],
        "defaultCode": 57344,
        "grid": 16,
        "colorPermutations": {
          "13636361": []
        }
      },
      "attrs": [],
      "properties": {
        "order": 51,
        "ligatures": "error",
        "id": 245,
        "prevSize": 18,
        "code": 57344,
        "name": "error"
      },
      "setIdx": 0,
      "setId": 0,
      "iconIdx": 63
    },
    {
      "icon": {
        "paths": [
          "M470 384v-86h84v86h-84zM512 854c188 0 342-154 342-342s-154-342-342-342-342 154-342 342 154 342 342 342zM512 86c236 0 426 190 426 426s-190 426-426 426-426-190-426-426 190-426 426-426zM470 726v-256h84v256h-84z"
        ],
        "attrs": [],
        "isMulticolor": false,
        "isMulticolor2": false,
        "tags": [
          "info_outline"
        ],
        "defaultCode": 59535,
        "grid": 16,
        "colorPermutations": {
          "13636361": []
        }
      },
      "attrs": [],
      "properties": {
        "order": 52,
        "ligatures": "info_outline",
        "id": 401,
        "prevSize": 18,
        "code": 59535,
        "name": "info_outline"
      },
      "setIdx": 0,
      "setId": 0,
      "iconIdx": 64
    },
    {
      "icon": {
        "paths": [
          "M554 384v-86h-84v86h84zM554 726v-256h-84v256h84zM512 86c236 0 426 190 426 426s-190 426-426 426-426-190-426-426 190-426 426-426z"
        ],
        "attrs": [],
        "isMulticolor": false,
        "isMulticolor2": false,
        "tags": [
          "info"
        ],
        "defaultCode": 59534,
        "grid": 16,
        "colorPermutations": {
          "13636361": []
        }
      },
      "attrs": [],
      "properties": {
        "order": 53,
        "ligatures": "info",
        "id": 400,
        "prevSize": 18,
        "code": 59534,
        "name": "info"
      },
      "setIdx": 0,
      "setId": 0,
      "iconIdx": 65
    },
    {
      "icon": {
        "paths": [
          "M554 554v-256h-84v256h84zM512 738c30 0 56-26 56-56s-26-54-56-54-56 24-56 54 26 56 56 56zM672 128l224 224v320l-224 224h-320l-224-224v-320l224-224h320z"
        ],
        "attrs": [],
        "isMulticolor": false,
        "isMulticolor2": false,
        "tags": [
          "report"
        ],
        "defaultCode": 57696,
        "grid": 16,
        "colorPermutations": {
          "13636361": []
        }
      },
      "attrs": [],
      "properties": {
        "order": 54,
        "ligatures": "report",
        "id": 631,
        "prevSize": 18,
        "code": 57696,
        "name": "report"
      },
      "setIdx": 0,
      "setId": 0,
      "iconIdx": 66
    },
    {
      "icon": {
        "paths": [
          "M554 598v-172h-84v172h84zM554 768v-86h-84v86h84zM42 896l470-810 470 810h-940z"
        ],
        "attrs": [],
        "isMulticolor": false,
        "isMulticolor2": false,
        "tags": [
          "warning"
        ],
        "defaultCode": 57346,
        "grid": 16,
        "colorPermutations": {
          "13636361": []
        }
      },
      "attrs": [],
      "properties": {
        "order": 55,
        "ligatures": "report_problem, warning",
        "id": 632,
        "prevSize": 18,
        "code": 57346,
        "name": "warning"
      },
      "setIdx": 0,
      "setId": 0,
      "iconIdx": 67
    },
    {
      "icon": {
        "paths": [
          "M426 128h172v512h-172v-512zM426 810c0-48 38-84 86-84s86 36 86 84-38 86-86 86-86-38-86-86z"
        ],
        "attrs": [],
        "isMulticolor": false,
        "isMulticolor2": false,
        "tags": [
          "priority_high"
        ],
        "defaultCode": 58949,
        "grid": 16,
        "colorPermutations": {
          "13636361": []
        }
      },
      "attrs": [],
      "properties": {
        "order": 56,
        "ligatures": "priority_high",
        "id": 604,
        "prevSize": 18,
        "code": 58949,
        "name": "priority_high"
      },
      "setIdx": 0,
      "setId": 0,
      "iconIdx": 68
    },
    {
      "icon": {
        "paths": [
          "M810 666l-152-154 152-154-60-60-152 154-154-154-60 60 154 154-154 154 60 60 154-154 152 154zM938 128c46 0 86 40 86 86v596c0 46-40 86-86 86h-640c-30 0-52-16-68-38l-230-346 230-346c16-22 38-38 68-38h640z"
        ],
        "attrs": [],
        "isMulticolor": false,
        "isMulticolor2": false,
        "tags": [
          "backspace"
        ],
        "defaultCode": 57674,
        "grid": 16,
        "colorPermutations": {
          "13636361": []
        }
      },
      "attrs": [],
      "properties": {
        "order": 57,
        "ligatures": "backspace",
        "id": 69,
        "prevSize": 18,
        "code": 57674,
        "name": "backspace"
      },
      "setIdx": 0,
      "setId": 0,
      "iconIdx": 69
    },
    {
      "icon": {
        "paths": [
          "M512 854c188 0 342-154 342-342 0-78-26-152-72-210l-480 480c58 46 132 72 210 72zM170 512c0 78 26 152 72 210l480-480c-58-46-132-72-210-72-188 0-342 154-342 342zM512 86c236 0 426 190 426 426s-190 426-426 426-426-190-426-426 190-426 426-426z"
        ],
        "attrs": [],
        "isMulticolor": false,
        "isMulticolor2": false,
        "tags": [
          "block"
        ],
        "defaultCode": 57675,
        "grid": 16,
        "colorPermutations": {
          "13636361": []
        }
      },
      "attrs": [],
      "properties": {
        "order": 58,
        "ligatures": "block",
        "id": 77,
        "prevSize": 18,
        "code": 57675,
        "name": "block"
      },
      "setIdx": 0,
      "setId": 0,
      "iconIdx": 70
    },
    {
      "icon": {
        "paths": [
          "M256 512h128l-170 170-172-170h128c0-188 154-342 342-342 66 0 130 20 182 54l-62 62c-36-20-76-30-120-30-142 0-256 114-256 256zM810 342l172 170h-128c0 188-154 342-342 342-66 0-130-20-182-54l62-62c36 20 76 30 120 30 142 0 256-114 256-256h-128z"
        ],
        "attrs": [],
        "isMulticolor": false,
        "isMulticolor2": false,
        "tags": [
          "cached"
        ],
        "defaultCode": 59498,
        "grid": 16,
        "colorPermutations": {
          "13636361": []
        }
      },
      "attrs": [],
      "properties": {
        "order": 59,
        "ligatures": "cached",
        "id": 118,
        "prevSize": 18,
        "code": 59498,
        "name": "cached"
      },
      "setIdx": 0,
      "setId": 0,
      "iconIdx": 71
    },
    {
      "icon": {
        "paths": [
          "M726 666l-154-154 154-154-60-60-154 154-154-154-60 60 154 154-154 154 60 60 154-154 154 154zM512 86c236 0 426 190 426 426s-190 426-426 426-426-190-426-426 190-426 426-426z"
        ],
        "attrs": [],
        "isMulticolor": false,
        "isMulticolor2": false,
        "tags": [
          "cancel"
        ],
        "defaultCode": 58825,
        "grid": 16,
        "colorPermutations": {
          "13636361": []
        }
      },
      "attrs": [],
      "properties": {
        "order": 60,
        "ligatures": "cancel",
        "id": 135,
        "prevSize": 18,
        "code": 58825,
        "name": "cancel"
      },
      "setIdx": 0,
      "setId": 0,
      "iconIdx": 72
    },
    {
      "icon": {
        "paths": [
          "M426 726l384-384-60-62-324 324-152-152-60 60zM810 128c48 0 86 40 86 86v596c0 46-38 86-86 86h-596c-48 0-86-40-86-86v-596c0-46 38-86 86-86h596z"
        ],
        "attrs": [],
        "isMulticolor": false,
        "isMulticolor2": false,
        "tags": [
          "check_box"
        ],
        "defaultCode": 59444,
        "grid": 16,
        "colorPermutations": {
          "13636361": []
        }
      },
      "attrs": [],
      "properties": {
        "order": 61,
        "ligatures": "check_box",
        "id": 149,
        "prevSize": 18,
        "code": 59444,
        "name": "check_box"
      },
      "setIdx": 0,
      "setId": 0,
      "iconIdx": 73
    },
    {
      "icon": {
        "paths": [
          "M726 554v-84h-428v84h428zM810 128c46 0 86 40 86 86v596c0 46-40 86-86 86h-596c-46 0-86-40-86-86v-596c0-46 40-86 86-86h596z"
        ],
        "attrs": [],
        "isMulticolor": false,
        "isMulticolor2": false,
        "tags": [
          "indeterminate_check_box"
        ],
        "defaultCode": 59657,
        "grid": 16,
        "colorPermutations": {
          "13636361": []
        }
      },
      "attrs": [],
      "properties": {
        "order": 62,
        "ligatures": "indeterminate_check_box",
        "id": 399,
        "prevSize": 18,
        "code": 59657,
        "name": "indeterminate_check_box"
      },
      "setIdx": 0,
      "setId": 0,
      "iconIdx": 74
    },
    {
      "icon": {
        "paths": [
          "M810 128c46 0 86 40 86 86v596c0 46-40 86-86 86h-596c-46 0-86-40-86-86v-596c0-46 40-86 86-86h596zM810 214h-596v596h596v-596z"
        ],
        "attrs": [],
        "isMulticolor": false,
        "isMulticolor2": false,
        "tags": [
          "check_box_outline_blank"
        ],
        "defaultCode": 59445,
        "grid": 16,
        "colorPermutations": {
          "13636361": []
        }
      },
      "attrs": [],
      "properties": {
        "order": 63,
        "ligatures": "check_box_outline_blank",
        "id": 150,
        "prevSize": 18,
        "code": 59445,
        "name": "check_box_outline_blank"
      },
      "setIdx": 0,
      "setId": 0,
      "iconIdx": 75
    },
    {
      "icon": {
        "paths": [
          "M512 854c188 0 342-154 342-342s-154-342-342-342-342 154-342 342 154 342 342 342zM512 86c236 0 426 190 426 426s-190 426-426 426-426-190-426-426 190-426 426-426zM512 298c118 0 214 96 214 214s-96 214-214 214-214-96-214-214 96-214 214-214z"
        ],
        "attrs": [],
        "isMulticolor": false,
        "isMulticolor2": false,
        "tags": [
          "radio_button_checked"
        ],
        "defaultCode": 59447,
        "grid": 16,
        "colorPermutations": {
          "13636361": []
        }
      },
      "attrs": [],
      "properties": {
        "order": 64,
        "ligatures": "radio_button_checked",
        "id": 610,
        "prevSize": 18,
        "code": 59447,
        "name": "radio_button_checked"
      },
      "setIdx": 0,
      "setId": 0,
      "iconIdx": 76
    },
    {
      "icon": {
        "paths": [
          "M512 854.016c187.989 0 342.016-153.984 342.016-342.016s-153.984-342.016-342.016-342.016-342.016 153.984-342.016 342.016 153.984 342.016 342.016 342.016zM512 86.016c235.989 0 425.984 189.995 425.984 425.984s-189.995 425.984-425.984 425.984-425.984-189.995-425.984-425.984 189.995-425.984 425.984-425.984z"
        ],
        "attrs": [],
        "isMulticolor": false,
        "isMulticolor2": false,
        "grid": 16,
        "tags": [
          "radio_button_unchecked"
        ],
        "colorPermutations": {
          "13636361": []
        }
      },
      "attrs": [],
      "properties": {
        "order": 65,
        "id": 848,
        "name": "radio_button_unchecked",
        "prevSize": 18,
        "code": 59656
      },
      "setIdx": 0,
      "setId": 0,
      "iconIdx": 77
    },
    {
      "icon": {
        "paths": [
          "M426 726l384-384-60-62-324 324-152-152-60 60zM512 86c236 0 426 190 426 426s-190 426-426 426-426-190-426-426 190-426 426-426z"
        ],
        "attrs": [],
        "isMulticolor": false,
        "isMulticolor2": false,
        "tags": [
          "check_circle"
        ],
        "defaultCode": 59500,
        "grid": 16,
        "colorPermutations": {
          "13636361": []
        }
      },
      "attrs": [],
      "properties": {
        "order": 66,
        "ligatures": "check_circle",
        "id": 151,
        "prevSize": 18,
        "code": 59500,
        "name": "check_circle"
      },
      "setIdx": 0,
      "setId": 0,
      "iconIdx": 78
    },
    {
      "icon": {
        "paths": [
          "M576 384h64v384h-64v-384z",
          "M320 384h64v384h-64v-384z",
          "M448 384h64v384h-64v-384z",
          "M960 192h-256v-128h-448v128h-256v64h128v542.080c-0.227 3.109-0.356 6.735-0.356 10.392 0 83.835 67.961 151.796 151.796 151.796 3.169 0 6.316-0.097 9.437-0.289l381.709 0.021c2.903 0.198 6.291 0.31 9.706 0.31 83.975 0 152.050-68.075 152.050-152.050 0-3.582-0.124-7.135-0.368-10.655l0.026-541.605h128zM320 128h320v64h-320zM768 798.080c0.358 2.988 0.562 6.447 0.562 9.955 0 48.864-39.612 88.477-88.477 88.477-3.347 0-6.651-0.186-9.901-0.548l-381.736 0.036c-2.573 0.266-5.56 0.417-8.582 0.417-48.835 0-88.424-39.589-88.424-88.424 0-3.493 0.203-6.939 0.597-10.326l-0.039-541.668h576z"
        ],
        "attrs": [
          {},
          {},
          {},
          {}
        ],
        "width": 960,
        "isMulticolor": false,
        "isMulticolor2": false,
        "grid": 16,
        "tags": [
          "composer_trash"
        ]
      },
      "attrs": [
        {},
        {},
        {},
        {}
      ],
      "properties": {
        "order": 82,
        "id": 20,
        "name": "composer_trash",
        "prevSize": 18,
        "code": 59648
      },
      "setIdx": 1,
      "setId": 1,
      "iconIdx": 0
    },
    {
      "icon": {
        "paths": [
          "M647.549 247.357l109.357-109.357v328.070h-328.070l150.912-150.912c-50.304-50.304-120.292-83.111-196.842-83.111-155.287 0-279.953 124.667-279.953 279.953s124.667 279.953 279.953 279.953c122.48 0 227.462-76.55 264.643-185.906h96.234c-41.556 161.848-185.906 279.953-360.877 279.953-205.591 0-371.813-168.409-371.813-374s166.222-374 371.813-374c102.795 0 196.842 41.556 264.643 109.357z"
        ],
        "attrs": [],
        "isMulticolor": false,
        "isMulticolor2": false,
        "tags": [
          "composer_refresh"
        ],
        "defaultCode": 58837,
        "grid": 16,
        "width": 768
      },
      "attrs": [],
      "properties": {
        "order": 83,
        "ligatures": "refresh",
        "id": 22,
        "prevSize": 18,
        "code": 58837,
        "name": "composer_refresh"
      },
      "setIdx": 1,
      "setId": 1,
      "iconIdx": 1
    },
    {
      "icon": {
        "paths": [
          "M493.717 648.966c0 111.808-84.934 183.86-231.412 183.86h-262.305v-641.014h231.394c127.833 0 200.964 62.684 200.964 157.141 0.060 1.501 0.094 3.263 0.094 5.033 0 60.683-40.287 111.957-95.574 128.534 86.933 5.502 156.284 77.787 156.838 166.391zM343.573 631.092c-0.064-55.596-46.813-85.458-107.185-85.458h-87.137v171.995h84.238c68.079 0 110.143-28.969 110.082-86.537zM214.167 307.008h-64.915v130.578l54.93 0.064c51.648 0.092 89.958-21.141 89.958-66.444 0.001-44.288-32.297-64.198-79.972-64.198z"
        ],
        "attrs": [
          {}
        ],
        "tags": [
          "composer_bold"
        ],
        "defaultCode": 57912,
        "grid": 16,
        "isMulticolor": false,
        "isMulticolor2": false,
        "width": 512
      },
      "attrs": [
        {}
      ],
      "properties": {
        "order": 84,
        "ligatures": "format_bold",
        "id": 1,
        "prevSize": 18,
        "code": 57912,
        "name": "composer_bold"
      },
      "setIdx": 1,
      "setId": 1,
      "iconIdx": 2
    },
    {
      "icon": {
        "paths": [
          "M253.604 697.356c-0.037 0.496-0.059 1.075-0.059 1.659 0 6.374 2.537 12.155 6.656 16.389 5.828 4.622 13.034 7.765 20.913 8.742 9.629 1.742 38.886 3.416 38.886 3.416v104.438h-320v-104.438c19.433-0.132 38.258-2.452 56.327-6.726 9.883-2.978 19.585-9.756 26.485-18.789 8.77-12.858 15.773-27.603 20.32-43.388s140.241-319.023 140.241-328.044c0.010-0.271 0.016-0.59 0.016-0.91 0-6.685-2.506-12.786-6.631-17.412-10.815-12.042-44.759-11.906-44.759-12.464v-107.829h320v107.829c-4.55-0.426-9.84-0.669-15.186-0.669-17.52 0-34.431 2.611-50.363 7.465-11.185 2.859-21.718 9.584-29.545 18.7-7.064 9.354-153.882 332.24-153.882 332.24-4.473 11.583-7.791 25.050-9.352 39.048z"
        ],
        "attrs": [
          {}
        ],
        "tags": [
          "composer_italic"
        ],
        "defaultCode": 57919,
        "grid": 16,
        "width": 512,
        "isMulticolor": false,
        "isMulticolor2": false
      },
      "attrs": [
        {}
      ],
      "properties": {
        "order": 85,
        "id": 15,
        "prevSize": 18,
        "code": 57919,
        "name": "composer_italic"
      },
      "setIdx": 1,
      "setId": 1,
      "iconIdx": 3
    },
    {
      "icon": {
        "paths": [
          "M448 192v640h-128v-256h-192v256h-128v-640h128v256h192v-256z",
          "M960 704v128h-384v-92.188l188.438-247.936c67.187-84.625 54.813-185.25-49.375-185.5-0.193-0.001-0.421-0.002-0.649-0.002-37.006 0-70.040 17.006-91.712 43.63l-74.467-82.1c42.205-52.758 106.579-86.258 178.778-86.258 4.456 0 8.882 0.128 13.275 0.379 2.323-0.189 5.752-0.28 9.203-0.28 105.273 0 190.614 85.341 190.614 190.614 0 2.269-0.040 4.528-0.118 6.778 0.009 88.799-51.176 140.643-111.176 214.923l-90.998 109.94z"
        ],
        "attrs": [
          {},
          {}
        ],
        "isMulticolor": false,
        "isMulticolor2": false,
        "grid": 16,
        "tags": [
          "composer_h2"
        ],
        "width": 960
      },
      "attrs": [
        {},
        {}
      ],
      "properties": {
        "order": 86,
        "id": 18,
        "name": "composer_h2",
        "prevSize": 18,
        "code": 59649
      },
      "setIdx": 1,
      "setId": 1,
      "iconIdx": 4
    },
    {
      "icon": {
        "paths": [
          "M448 192v640h-128v-256h-192v256h-128v-640h128v256h192v-256z",
          "M990.666 651.544c0 110.569-66.42 197.331-220.25 197.331-2.592 0.065-5.646 0.102-8.707 0.102-77.993 0-150.395-23.937-210.261-64.865l61.906-117.236c37.532 29.115 84.756 47.403 136.156 49.485 68.907-0.735 103.969-25.547 103.969-68.61 0-52.999-51.751-71.751-121.127-71.751h-41.875l-35-89.703 137.752-166.297h-217.229v-128h384v97.25l-156.58 181.461c100.335 2.12 181.554 81.107 187.223 180.325z"
        ],
        "attrs": [
          {},
          {}
        ],
        "isMulticolor": false,
        "isMulticolor2": false,
        "grid": 16,
        "tags": [
          "composer_h3"
        ],
        "width": 992
      },
      "attrs": [
        {},
        {}
      ],
      "properties": {
        "order": 87,
        "id": 17,
        "name": "composer_h3",
        "prevSize": 18,
        "code": 59650
      },
      "setIdx": 1,
      "setId": 1,
      "iconIdx": 5
    },
    {
      "icon": {
        "paths": [
          "M448 192v640h-128v-256h-192v256h-128v-640h128v256h192v-256z",
          "M1024 705.92l-64-0.128v126.208h-128v-126.582l-320-0.687v-100.043l290.015-412.687h157.985l-285.632 384h157.632v-128h128v128h64z"
        ],
        "attrs": [
          {},
          {}
        ],
        "isMulticolor": false,
        "isMulticolor2": false,
        "grid": 16,
        "tags": [
          "composer_h4"
        ]
      },
      "attrs": [
        {},
        {}
      ],
      "properties": {
        "order": 88,
        "id": 16,
        "name": "composer_h4",
        "prevSize": 18,
        "code": 59651
      },
      "setIdx": 1,
      "setId": 1,
      "iconIdx": 6
    },
    {
      "icon": {
        "paths": [
          "M165 812l344-344-82-82-344 344zM753 242c16 16 18 42 0 60l-134 134 82 82-60 60-60-60-382 380h-202v-202l380-382-60-60 60-60 82 82 134-134c16-16 44-16 60 0z"
        ],
        "attrs": [],
        "isMulticolor": false,
        "isMulticolor2": false,
        "tags": [
          "composer_colorize"
        ],
        "defaultCode": 58296,
        "grid": 16,
        "width": 768
      },
      "attrs": [],
      "properties": {
        "order": 89,
        "ligatures": "colorize",
        "id": 13,
        "prevSize": 18,
        "code": 58296,
        "name": "composer_colorize"
      },
      "setIdx": 1,
      "setId": 1,
      "iconIdx": 7
    },
    {
      "icon": {
        "paths": [
          "M0 192h896v96h-896v-96z",
          "M0 464h512v96h-512v-96z",
          "M0 736h768v96h-768v-96z"
        ],
        "attrs": [
          {},
          {},
          {}
        ],
        "tags": [
          "composer_align_left"
        ],
        "defaultCode": 57910,
        "grid": 16,
        "isMulticolor": false,
        "isMulticolor2": false,
        "width": 896
      },
      "attrs": [
        {},
        {},
        {}
      ],
      "properties": {
        "order": 90,
        "id": 25,
        "name": "composer_align_left",
        "prevSize": 18,
        "code": 57910
      },
      "setIdx": 1,
      "setId": 1,
      "iconIdx": 8
    },
    {
      "icon": {
        "paths": [
          "M0 192h896v96h-896v-96z",
          "M224 464h448v96h-448v-96z",
          "M64 736h768v96h-768v-96z"
        ],
        "attrs": [
          {},
          {},
          {}
        ],
        "tags": [
          "composer_align_center"
        ],
        "defaultCode": 57908,
        "grid": 16,
        "isMulticolor": false,
        "isMulticolor2": false,
        "width": 896
      },
      "attrs": [
        {},
        {},
        {}
      ],
      "properties": {
        "order": 91,
        "id": 27,
        "name": "composer_align_center",
        "prevSize": 18,
        "code": 57908
      },
      "setIdx": 1,
      "setId": 1,
      "iconIdx": 9
    },
    {
      "icon": {
        "paths": [
          "M0.001 192h896v96h-896v-96z",
          "M384.001 464h512v96h-512v-96z",
          "M128.001 736h768v96h-768v-96z"
        ],
        "attrs": [
          {},
          {},
          {}
        ],
        "tags": [
          "composer_align_right"
        ],
        "defaultCode": 57911,
        "grid": 16,
        "isMulticolor": false,
        "isMulticolor2": false,
        "width": 896
      },
      "attrs": [
        {},
        {},
        {}
      ],
      "properties": {
        "order": 92,
        "id": 28,
        "name": "composer_align_right",
        "prevSize": 18,
        "code": 57911
      },
      "setIdx": 1,
      "setId": 1,
      "iconIdx": 10
    },
    {
      "icon": {
        "paths": [
          "M197 214h598v84h-598v-84zM197 554v-84h598v84h-598zM197 810v-84h598v84h-598zM69 704c36 0 64 30 64 64s-30 64-64 64-64-30-64-64 28-64 64-64zM69 192c36 0 64 28 64 64s-28 64-64 64-64-28-64-64 28-64 64-64zM69 448c36 0 64 28 64 64s-28 64-64 64-64-28-64-64 28-64 64-64z"
        ],
        "attrs": [],
        "isMulticolor": false,
        "isMulticolor2": false,
        "tags": [
          "composer_list_bulleted"
        ],
        "defaultCode": 57921,
        "grid": 16,
        "width": 800
      },
      "attrs": [],
      "properties": {
        "order": 93,
        "ligatures": "format_list_bulleted",
        "id": 19,
        "prevSize": 18,
        "code": 57921,
        "name": "composer_list_bulleted"
      },
      "setIdx": 1,
      "setId": 1,
      "iconIdx": 11
    },
    {
      "icon": {
        "paths": [
          "M234.004 554v-84h598v84h-598zM234.004 810v-84h598v84h-598zM234.004 214h598v84h-598v-84zM22.004 470v-44h128v40l-78 88h78v44h-128v-40l76-88h-76zM64.004 342v-128h-42v-44h84v172h-42zM22.004 726v-44h128v172h-128v-44h84v-20h-42v-44h42v-20h-84z"
        ],
        "attrs": [],
        "isMulticolor": false,
        "isMulticolor2": false,
        "tags": [
          "composer_list_numbered"
        ],
        "defaultCode": 57922,
        "grid": 16,
        "width": 832
      },
      "attrs": [],
      "properties": {
        "order": 94,
        "ligatures": "format_list_numbered",
        "id": 8,
        "prevSize": 18,
        "code": 57922,
        "name": "composer_list_numbered"
      },
      "setIdx": 1,
      "setId": 1,
      "iconIdx": 12
    },
    {
      "icon": {
        "paths": [
          "M0 496h1024v96h-1024v-96z"
        ],
        "attrs": [
          {}
        ],
        "grid": 16,
        "tags": [
          "composer_dividing_line"
        ],
        "isMulticolor": false,
        "isMulticolor2": false
      },
      "attrs": [
        {}
      ],
      "properties": {
        "order": 95,
        "id": 21,
        "name": "composer_dividing_line",
        "prevSize": 18,
        "code": 59662
      },
      "setIdx": 1,
      "setId": 1,
      "iconIdx": 13
    },
    {
      "icon": {
        "paths": [
          "M885.77 511.999c0.551-4.848 0.865-10.467 0.865-16.159 0-83.607-67.776-151.383-151.383-151.383-4.971 0-9.886 0.24-14.734 0.708l-171.16-0.048v-71.982h171.776c1.891-0.056 4.116-0.087 6.348-0.087 127.262 0 230.428 103.166 230.428 230.428 0 2.998-0.057 5.982-0.171 8.952 0.113 2.114 0.171 5.099 0.171 8.096 0 127.262-103.166 230.428-230.428 230.428-2.232 0-4.457-0.032-6.674-0.095l-171.45 0.007v-71.982h171.776c90.75-2.35 163.552-75.938 164.636-166.778zM74.232 511.999c1.086 90.945 73.892 164.533 164.425 166.875l171.99 0.004v71.981h-171.772c-1.901 0.056-4.137 0.088-6.38 0.088-127.249 0-230.404-103.155-230.404-230.404 0-3.005 0.058-5.997 0.172-8.974-0.114-2.119-0.172-5.111-0.172-8.116 0-127.249 103.155-230.404 230.404-230.404 2.243 0 4.479 0.032 6.707 0.096l171.444-0.007v71.985h-171.772c-4.23-0.42-9.143-0.659-14.112-0.659-83.613 0-151.395 67.782-151.395 151.395 0 5.686 0.313 11.298 0.924 16.821zM287.984 559.971v-96h379.478v96z"
        ],
        "attrs": [
          {}
        ],
        "tags": [
          "composer_link"
        ],
        "defaultCode": 57687,
        "grid": 16,
        "isMulticolor": false,
        "isMulticolor2": false,
        "width": 960
      },
      "attrs": [
        {}
      ],
      "properties": {
        "order": 96,
        "id": 24,
        "name": "composer_link",
        "prevSize": 18,
        "code": 57687
      },
      "setIdx": 1,
      "setId": 1,
      "iconIdx": 14
    },
    {
      "icon": {
        "paths": [
          "M1024 780.071c-1.85 64.428-54.52 115.951-119.224 115.951-0.81 0-1.618-0.008-2.424-0.024l-780.824 0.002c-0.686 0.014-1.494 0.022-2.303 0.022-64.704 0-117.374-51.524-119.22-115.781l-0.405-536.56c1.872-64.298 54.442-115.708 119.019-115.708 0.882 0 1.762 0.010 2.639 0.029l780.813-0.002c0.747-0.017 1.626-0.026 2.508-0.026 64.578 0 117.148 51.41 119.016 115.536zM959.599 250.84c0.001-0.109 0.001-0.239 0.001-0.368 0-32.072-25.819-58.113-57.806-58.472l-780.358-0c-32.020 0.36-57.838 26.401-57.838 58.472 0 0.129 0 0.259 0.001 0.388l0.401 521.253c-0.001 0.153-0.002 0.334-0.002 0.515 0 32.255 25.713 58.505 57.759 59.37l780.406 0.002c32.126-0.867 57.839-27.116 57.839-59.372 0-0.181-0.001-0.362-0.002-0.543z",
          "M320 514.048l-128.832 189.952h640.832l-192.704-289.856-234.048 225.216-85.248-125.312z"
        ],
        "attrs": [
          {},
          {}
        ],
        "isMulticolor": false,
        "isMulticolor2": false,
        "grid": 16,
        "tags": [
          "composer_image"
        ]
      },
      "attrs": [
        {},
        {}
      ],
      "properties": {
        "order": 97,
        "id": 14,
        "name": "composer_image",
        "prevSize": 18,
        "code": 59652
      },
      "setIdx": 1,
      "setId": 1,
      "iconIdx": 15
    },
    {
      "icon": {
        "paths": [
          "M0 128v768h1024v-768zM169.412 836.923h-112.941v-118.154h112.941zM169.412 659.692h-112.941v-118.154h112.941zM169.412 482.461h-112.941v-118.154h112.941zM169.412 305.231h-112.941v-118.154h112.941zM798.118 836.923h-572.236v-649.846h572.236zM967.53 836.923h-112.941v-118.154h112.941zM967.53 659.692h-112.941v-118.154h112.941zM967.53 482.461h-112.941v-118.154h112.941zM967.53 305.231h-112.941v-118.154h112.941z",
          "M384 653.184v-282.368l282.368 141.184-282.368 141.184z"
        ],
        "attrs": [
          {},
          {}
        ],
        "tags": [
          "composer_video"
        ],
        "grid": 16,
        "isMulticolor": false,
        "isMulticolor2": false
      },
      "attrs": [
        {},
        {}
      ],
      "properties": {
        "order": 98,
        "id": 0,
        "name": "composer_video",
        "prevSize": 18,
        "code": 59653
      },
      "setIdx": 1,
      "setId": 1,
      "iconIdx": 16
    },
    {
      "icon": {
        "paths": [
          "M73.143 950.857h164.571v-164.571h-164.571v164.571zM274.286 950.857h182.857v-164.571h-182.857v164.571zM73.143 749.714h164.571v-182.857h-164.571v182.857zM274.286 749.714h182.857v-182.857h-182.857v182.857zM73.143 530.286h164.571v-164.571h-164.571v164.571zM493.714 950.857h182.857v-164.571h-182.857v164.571zM274.286 530.286h182.857v-164.571h-182.857v164.571zM713.143 950.857h164.571v-164.571h-164.571v164.571zM493.714 749.714h182.857v-182.857h-182.857v182.857zM292.571 256v-164.571c0-9.714-8.571-18.286-18.286-18.286h-36.571c-9.714 0-18.286 8.571-18.286 18.286v164.571c0 9.714 8.571 18.286 18.286 18.286h36.571c9.714 0 18.286-8.571 18.286-18.286zM713.143 749.714h164.571v-182.857h-164.571v182.857zM493.714 530.286h182.857v-164.571h-182.857v164.571zM713.143 530.286h164.571v-164.571h-164.571v164.571zM731.429 256v-164.571c0-9.714-8.571-18.286-18.286-18.286h-36.571c-9.714 0-18.286 8.571-18.286 18.286v164.571c0 9.714 8.571 18.286 18.286 18.286h36.571c9.714 0 18.286-8.571 18.286-18.286zM950.857 219.429v731.429c0 40-33.143 73.143-73.143 73.143h-804.571c-40 0-73.143-33.143-73.143-73.143v-731.429c0-40 33.143-73.143 73.143-73.143h73.143v-54.857c0-50.286 41.143-91.429 91.429-91.429h36.571c50.286 0 91.429 41.143 91.429 91.429v54.857h219.429v-54.857c0-50.286 41.143-91.429 91.429-91.429h36.571c50.286 0 91.429 41.143 91.429 91.429v54.857h73.143c40 0 73.143 33.143 73.143 73.143z"
        ],
        "attrs": [
          {}
        ],
        "width": 951,
        "isMulticolor": false,
        "isMulticolor2": false,
        "tags": [
          "calendar"
        ],
        "grid": 14
      },
      "attrs": [
        {}
      ],
      "properties": {
        "order": 2,
        "id": 856,
        "name": "calendar",
        "prevSize": 28,
        "code": 59666
      },
      "setIdx": 0,
      "setId": 0,
      "iconIdx": 79
    },
    {
      "icon": {
        "paths": [
          "M992 32v960h-960v-960h960zM1024 0h-1024v1024h1024v-1024z",
          "M128 128h512v768h-512v-768z",
          "M704 128h192v768h-192v-768z"
        ],
        "attrs": [
          {},
          {},
          {}
        ],
        "grid": 32,
        "tags": [
          "layout_standard"
        ],
        "isMulticolor": false,
        "isMulticolor2": false
      },
      "attrs": [
        {},
        {},
        {}
      ],
      "properties": {
        "order": 99,
        "id": 0,
        "name": "layout_standard",
        "prevSize": 24,
        "code": 59663
      },
      "setIdx": 2,
      "setId": 3,
      "iconIdx": 0
    },
    {
      "icon": {
        "paths": [
          "M992 32v960h-960v-960h960zM1024 0h-1024v1024h1024v-1024z",
          "M128 128h768v768h-768v-768z"
        ],
        "attrs": [
          {},
          {}
        ],
        "grid": 32,
        "tags": [
          "layout_full"
        ],
        "isMulticolor": false,
        "isMulticolor2": false
      },
      "attrs": [
        {},
        {}
      ],
      "properties": {
        "order": 100,
        "id": 2,
        "name": "layout_full",
        "prevSize": 24,
        "code": 59664
      },
      "setIdx": 2,
      "setId": 3,
      "iconIdx": 1
    },
    {
      "icon": {
        "paths": [
          "M992 32v960h-960v-960h960zM1024 0h-1024v1024h1024v-1024z",
          "M0 128h1024v768h-1024v-768z"
        ],
        "attrs": [
          {},
          {}
        ],
        "grid": 32,
        "tags": [
          "layout_hero"
        ],
        "isMulticolor": false,
        "isMulticolor2": false
      },
      "attrs": [
        {},
        {}
      ],
      "properties": {
        "order": 101,
        "id": 1,
        "name": "layout_hero",
        "prevSize": 24,
        "code": 59665
      },
      "setIdx": 2,
      "setId": 3,
      "iconIdx": 2
    }
  ],
  "height": 1024,
  "metadata": {
    "name": "parfait-iconfont",
    "designer": "CQL"
  },
  "preferences": {
    "showGlyphs": true,
    "showCodes": false,
    "showQuickUse": true,
    "showQuickUse2": true,
    "showSVGs": true,
    "fontPref": {
      "prefix": "icon-",
      "metadata": {
        "fontFamily": "parfait-iconfont",
        "majorVersion": 1,
        "minorVersion": 0,
        "designer": "CQL"
      },
      "metrics": {
        "emSize": 1024,
        "baseline": 6.25,
        "whitespace": 50
      },
      "embed": false,
      "noie8": false,
      "ie7": false,
      "cssVars": false,
      "cssVarsFormat": "scss",
      "showSelector": true,
      "showMetrics": false,
      "showMetadata": false,
      "showVersion": false,
      "selector": "i"
    },
    "imagePref": {
      "prefix": "icon-",
      "png": true,
      "useClassSelector": true,
      "color": 0,
      "bgColor": 16777215,
      "classSelector": ".icon"
    },
    "historySize": 100,
    "gridSize": 16,
    "showGrid": true,
    "showLiga": false
  }
}